pymllm/.gitignore
pymllm/README.md
pymllm/__init__.py
pymllm/bin/mllm-params-inspector
pymllm/bin/mllm-quantizer
pymllm/compile/__init__.py
pymllm/convertor/__init__.py
pymllm/convertor/mllm_type_mapping.py
pymllm/convertor/model_file_v1.py
pymllm/convertor/model_file_v2.py
pymllm/ffi/__init__.py
pymllm/ffi/_ffi_api.py
pymllm/ffi/base.py
pymllm/include/dlpack/dlpack.h
pymllm/include/exec/__detail/__atomic_intrusive_queue.hpp
pymllm/include/exec/__detail/__atomic_ref.hpp
pymllm/include/exec/__detail/__basic_sequence.hpp
pymllm/include/exec/__detail/__bit_cast.hpp
pymllm/include/exec/__detail/__bwos_lifo_queue.hpp
pymllm/include/exec/__detail/__numa.hpp
pymllm/include/exec/__detail/__system_context_default_impl.hpp
pymllm/include/exec/__detail/__system_context_default_impl_entry.hpp
pymllm/include/exec/__detail/__system_context_replaceability_api.hpp
pymllm/include/exec/__detail/__xorshift.hpp
pymllm/include/exec/__detail/intrusive_heap.hpp
pymllm/include/exec/any_sender_of.hpp
pymllm/include/exec/async_scope.hpp
pymllm/include/exec/at_coroutine_exit.hpp
pymllm/include/exec/create.hpp
pymllm/include/exec/env.hpp
pymllm/include/exec/finally.hpp
pymllm/include/exec/inline_scheduler.hpp
pymllm/include/exec/into_tuple.hpp
pymllm/include/exec/just_from.hpp
pymllm/include/exec/libdispatch_queue.hpp
pymllm/include/exec/linux/__detail/memory_mapped_region.hpp
pymllm/include/exec/linux/__detail/safe_file_descriptor.hpp
pymllm/include/exec/linux/io_uring_context.hpp
pymllm/include/exec/linux/memory_mapped_region.hpp
pymllm/include/exec/linux/safe_file_descriptor.hpp
pymllm/include/exec/materialize.hpp
pymllm/include/exec/on.hpp
pymllm/include/exec/on_coro_disposition.hpp
pymllm/include/exec/repeat_effect_until.hpp
pymllm/include/exec/repeat_n.hpp
pymllm/include/exec/reschedule.hpp
pymllm/include/exec/scope.hpp
pymllm/include/exec/sequence/any_sequence_of.hpp
pymllm/include/exec/sequence/empty_sequence.hpp
pymllm/include/exec/sequence/ignore_all_values.hpp
pymllm-2.0.1.dist-info/METADATA
pymllm-2.0.1.dist-info/WHEEL
pymllm-2.0.1.dist-info/entry_points.txt
pymllm-2.0.1.dist-info/licenses/LICENSE
pymllm-2.0.1.dist-info/licenses/AUTHORS
pymllm-2.0.1.dist-info/RECORD
