Metadata-Version: 2.1
Name: pymllm
Version: 2.0.1
Summary: Fast and lightweight multimodal LLM inference engine for mobile and edge devices
Keywords: pymllm,llm,inference,machine learning
Author-Email: "chenghua.wang" <chenghua.wang.edu@gmail.com>
Requires-Python: >=3.10
Requires-Dist: packaging
Requires-Dist: pytest
Requires-Dist: pytest-html
Requires-Dist: apache-tvm-ffi==0.1.0b4
Requires-Dist: pyyaml>=6.0.2
Requires-Dist: openai
Requires-Dist: modelscope
Requires-Dist: fastapi
Requires-Dist: uvicorn
